linchpin/__init__.py
linchpin/ansible_runner.py
linchpin/callbacks.py
linchpin/context.py
linchpin/galaxy_runner.py
linchpin/linchpin.constants
linchpin/version.py
linchpin/FilterUtils/FilterUtils.py
linchpin/FilterUtils/__init__.py
linchpin/InventoryFilters/CFGInventoryFormatter.py
linchpin/InventoryFilters/GenericInventory.py
linchpin/InventoryFilters/InventoryFilter.py
linchpin/InventoryFilters/InventoryFormatter.py
linchpin/InventoryFilters/InventoryProviders.py
linchpin/InventoryFilters/JSONInventoryFormatter.py
linchpin/InventoryFilters/__init__.py
linchpin/MockUtils/MockUtils.py
linchpin/MockUtils/__init__.py
linchpin/MockUtils/aws_s3.data
linchpin/MockUtils/azure_availabilityset.absent.data
linchpin/MockUtils/azure_availabilityset.present.data
linchpin/MockUtils/azure_loadbalancer.absent.data
linchpin/MockUtils/azure_loadbalancer.present.data
linchpin/MockUtils/azure_network_interface.absent.data
linchpin/MockUtils/azure_network_interface.present.data
linchpin/MockUtils/azure_nsg.absent.data
linchpin/MockUtils/azure_nsg.present.data
linchpin/MockUtils/azure_publicaddress.absent.data
linchpin/MockUtils/azure_publicaddress.present.data
linchpin/MockUtils/azure_resource_group.absent.data
linchpin/MockUtils/azure_resource_group.present.data
linchpin/MockUtils/azure_storage_account.absent.data
linchpin/MockUtils/azure_storage_account.present.data
linchpin/MockUtils/azure_virtual_network.absent.data
linchpin/MockUtils/azure_virtual_network.present.data
linchpin/MockUtils/azure_virtual_subnet.absent.data
linchpin/MockUtils/azure_virtual_subnet.present.data
linchpin/MockUtils/azure_vm.absent.data
linchpin/MockUtils/azure_vm.present.data
linchpin/MockUtils/beaker_info.data
linchpin/MockUtils/beaker_server.data
linchpin/MockUtils/command_aas.data
linchpin/MockUtils/command_gxmldov.data
linchpin/MockUtils/command_mkisofs.data
linchpin/MockUtils/command_remove_cd.data
linchpin/MockUtils/copy_CISTMNN.data
linchpin/MockUtils/ec2.data
linchpin/MockUtils/ec2_eip.data
linchpin-2.0.4.1.dist-info/LICENSE
linchpin-2.0.4.1.dist-info/METADATA
linchpin-2.0.4.1.dist-info/WHEEL
linchpin-2.0.4.1.dist-info/entry_points.txt
linchpin-2.0.4.1.dist-info/top_level.txt
linchpin-2.0.4.1.dist-info/RECORD
